ss.py
ss-1.6.0.data/scripts/ss.py
ss-1.6.0.dist-info/DESCRIPTION.rst
ss-1.6.0.dist-info/METADATA
ss-1.6.0.dist-info/RECORD
ss-1.6.0.dist-info/WHEEL
ss-1.6.0.dist-info/entry_points.txt
ss-1.6.0.dist-info/metadata.json
ss-1.6.0.dist-info/pbr.json
ss-1.6.0.dist-info/top_level.txt
