Metadata-Version: 2.0
Name: ss
Version: 1.6.0
Summary: Command line script that automatically searches for video subtitles using OpenSubtitles.org APIs.
Home-page: http://nicoddemus.github.io/ss/
Author: nicoddemus@gmail.com
Author-email: nicoddemus@gmail.com
License: GPL
Keywords: subtitles script
Platform: UNKNOWN
Classifier: Development Status :: 5 - Production/Stable
Classifier: Environment :: Console
Classifier: Intended Audience :: End Users/Desktop
Classifier: License :: OSI Approved :: GNU General Public License v3 (GPLv3)
Classifier: Operating System :: OS Independent
Classifier: Programming Language :: Python :: 2.7
Classifier: Programming Language :: Python :: 3
Classifier: Programming Language :: Python :: 3.3
Classifier: Programming Language :: Python :: 3.4
Classifier: Programming Language :: Python :: 3.5
Requires-Dist: colorama
Requires-Dist: guessit (>=2)
Requires-Dist: futures; python_version=="2.7"
